telegram_easy/__init__.py
telegram_easy/_core.py
telegram_easy/cli.py
telegram_easy/send_receive.py
telegram_easy/aio/__init__.py
telegram_easy/aio/send_receive.py
telegram_easy-0.2.0.dist-info/licenses/LICENSE
telegram_easy-0.2.0.dist-info/METADATA
telegram_easy-0.2.0.dist-info/WHEEL
telegram_easy-0.2.0.dist-info/entry_points.txt
telegram_easy-0.2.0.dist-info/top_level.txt
telegram_easy-0.2.0.dist-info/RECORD
