Metadata-Version: 2.4
Name: telegram-easy
Version: 0.2.0
Summary: A very simple Python package to send and receive Telegram messages
Author-email: Ferran Busquets <ferranb@gmail.com>
License-Expression: MIT
Project-URL: Homepage, https://github.com/ferranb/telegram-easy
Keywords: telegram,bot,automation
Classifier: Programming Language :: Python :: 3
Classifier: Operating System :: OS Independent
Requires-Python: >=3.8
License-File: LICENSE
Requires-Dist: httpx
Dynamic: license-file
